orionTools/__init__.py
orionTools/httpd/__init__.py
orionTools/httpd/server.py
orionTools/utils/__init__.py
orionTools/utils/files_op.py
orionTools/utils/my_res.py
orionTools/utils/str_op.py
orionTools-0.0.4.dist-info/LICENSE
orionTools-0.0.4.dist-info/METADATA
orionTools-0.0.4.dist-info/WHEEL
orionTools-0.0.4.dist-info/top_level.txt
orionTools-0.0.4.dist-info/RECORD
