Metadata-Version: 2.1
Name: orionTools
Version: 0.0.4
Summary: orion tools
Home-page: https://github.com/eqauto/orion-tools.git
Author: eqauto
Author-email: eqauto@yeah.net
License: MIT
Keywords: orion,orionTools
Platform: any
License-File: LICENSE
